redeconv/ReDeconv_Normalization.py
redeconv/ReDeconv_Percentage.py
redeconv/__ReDeconv_N.py
redeconv/__ReDeconv_P.py
redeconv/__init__.py
redeconv-1.2.1.dist-info/LICENSE
redeconv-1.2.1.dist-info/METADATA
redeconv-1.2.1.dist-info/WHEEL
redeconv-1.2.1.dist-info/top_level.txt
redeconv-1.2.1.dist-info/RECORD
